setup.py
sigdebug/__init__.py
sigdebug.egg-info/PKG-INFO
sigdebug.egg-info/SOURCES.txt
sigdebug.egg-info/dependency_links.txt
sigdebug.egg-info/top_level.txt