Metadata-Version: 1.0
Name: sigdebug
Version: 0.2
Summary: Debug helpers responding to signals
Home-page: UNKNOWN
Author: Ryan P. Kelly
Author-email: rpkelly22@gmail.com
License: UNKNOWN
Platform: UNKNOWN
Classifier: Development Status :: 4 - Beta
Classifier: Intended Audience :: Developers
Classifier: License :: OSI Approved :: BSD License
Classifier: Operating System :: OS Independent
Classifier: Programming Language :: Python
Classifier: Topic :: Software Development :: Debuggers
